pur/__about__.py
pur/__init__.py
pur/__main__.py
pur/exceptions.py
pur/utils.py
pur/packages/__init__.py
pur/packages/pip/__init__.py
pur/packages/pip/__main__.py
pur/packages/pip/_internal/__init__.py
pur/packages/pip/_internal/build_env.py
pur/packages/pip/_internal/cache.py
pur/packages/pip/_internal/configuration.py
pur/packages/pip/_internal/exceptions.py
pur/packages/pip/_internal/main.py
pur/packages/pip/_internal/pyproject.py
pur/packages/pip/_internal/self_outdated_check.py
pur/packages/pip/_internal/wheel_builder.py
pur/packages/pip/_internal/cli/__init__.py
pur/packages/pip/_internal/cli/autocompletion.py
pur/packages/pip/_internal/cli/base_command.py
pur/packages/pip/_internal/cli/cmdoptions.py
pur/packages/pip/_internal/cli/command_context.py
pur/packages/pip/_internal/cli/main.py
pur/packages/pip/_internal/cli/main_parser.py
pur/packages/pip/_internal/cli/parser.py
pur/packages/pip/_internal/cli/progress_bars.py
pur/packages/pip/_internal/cli/req_command.py
pur/packages/pip/_internal/cli/spinners.py
pur/packages/pip/_internal/cli/status_codes.py
pur/packages/pip/_internal/commands/__init__.py
pur/packages/pip/_internal/commands/cache.py
pur/packages/pip/_internal/commands/check.py
pur/packages/pip/_internal/commands/completion.py
pur/packages/pip/_internal/commands/configuration.py
pur/packages/pip/_internal/commands/debug.py
pur/packages/pip/_internal/commands/download.py
pur/packages/pip/_internal/commands/freeze.py
pur/packages/pip/_internal/commands/hash.py
pur/packages/pip/_internal/commands/help.py
pur/packages/pip/_internal/commands/index.py
pur/packages/pip/_internal/commands/install.py
pur/packages/pip/_internal/commands/list.py
pur/packages/pip/_internal/commands/search.py
pur/packages/pip/_internal/commands/show.py
pur/packages/pip/_internal/commands/uninstall.py
pur/packages/pip/_internal/commands/wheel.py
pur/packages/pip/_internal/distributions/__init__.py
pur/packages/pip/_internal/distributions/base.py
pur-7.0.0.dist-info/AUTHORS
pur-7.0.0.dist-info/LICENSE
pur-7.0.0.dist-info/METADATA
pur-7.0.0.dist-info/NOTICE
pur-7.0.0.dist-info/WHEEL
pur-7.0.0.dist-info/entry_points.txt
pur-7.0.0.dist-info/top_level.txt
pur-7.0.0.dist-info/RECORD
