Metadata-Version: 2.1
Name: pur
Version: 7.0.0
Summary: Update packages in a requirements.txt file to latest versions.
Home-page: https://github.com/alanhamlett/pip-update-requirements
Author: Alan Hamlett
Author-email: alan.hamlett@gmail.com
License: BSD
Platform: any
Classifier: Development Status :: 5 - Production/Stable
Classifier: Environment :: Console
Classifier: Intended Audience :: Developers
Classifier: License :: OSI Approved :: BSD License
Classifier: Natural Language :: English
Classifier: Programming Language :: Python
Classifier: Programming Language :: Python :: 3
Classifier: Programming Language :: Python :: 3.7
Classifier: Programming Language :: Python :: 3.8
Classifier: Programming Language :: Python :: 3.9
Classifier: Programming Language :: Python :: 3.10
Classifier: Topic :: Software Development :: Build Tools
License-File: LICENSE
License-File: NOTICE
License-File: AUTHORS
